pyitcast/__init__.py
pyitcast/transformer.py
pyitcast/transformer_utils.py
pyitcast-1.0.4.dist-info/DESCRIPTION.rst
pyitcast-1.0.4.dist-info/METADATA
pyitcast-1.0.4.dist-info/RECORD
pyitcast-1.0.4.dist-info/WHEEL
pyitcast-1.0.4.dist-info/metadata.json
pyitcast-1.0.4.dist-info/top_level.txt
pyoneline/__init__.py
pyoneline/transformer_utils.py
