Metadata-Version: 2.0
Name: pyitcast
Version: 1.0.4
Summary: 传智播客开源分享工具包!
Home-page: https://github.com/StephenZMZ/OneLine.git
Author: Stephen.Z
Author-email: 15242200221@163.com
License: MIT
Keywords: python itcast
Platform: UNKNOWN
Classifier: Intended Audience :: Developers
Classifier: Topic :: Software Development :: Build Tools
Classifier: License :: OSI Approved :: MIT License
Classifier: Programming Language :: Python :: 2.6
Classifier: Programming Language :: Python :: 2.7
Classifier: Programming Language :: Python :: 3
Classifier: Programming Language :: Python :: 3.3
Classifier: Programming Language :: Python :: 3.4
Classifier: Programming Language :: Python :: 3.5
